[
  {
    "id": "top_01",
    "title": "'은행 문턱' 높이자 카드사로…카드론 43조 돌파, 취약차주 연체 경보",
    "publisher": "ziksir.com",
    "published_at": "2026-06-24T00:00:00+09:00",
    "checkyn": "Y",
    "summary": "[직썰 / 이연주 기자] 정부와 금융권이 가계부채를 억제하기 위해 은행권 대출 규제를 강화하자 급전이 필요한 서민들이 카드사로 몰려들고 있다. 다만 고금리 카드론 잔액이 43조원을 돌파하며 역대 최대치를 경신한 가운데, 취약차주의 이자 부담이 커지면서 연체율 상승 등 부실 폭탄으로 이어질 수 있다. ◇고물가·생활고에 은행 막히자…카드론 한 달 새 2705억 급증 22일 여신금융협회에 따르면 국내 9개 카드사(롯데·비씨·삼성·신한·우리·하나·현대·국민·농협)의 카드론 잔액은 43조2534억원으로 집계됐다.",
    "keywords": [
      "가계대출",
      "가계부채",
      "금융감독원 대출",
      "금융소비자",
      "대출 규제",
      "대출 금리",
      "대환대출",
      "신용대출"
    ],
    "auto_keywords": [
      "가계대출",
      "가계부채",
      "금융감독원 대출",
      "금융소비자",
      "대출 규제",
      "대출 금리",
      "대환대출",
      "신용대출"
    ],
    "auto_key_sentences": [
      "[직썰 / 이연주 기자] 정부와 금융권이 가계부채를 억제하기 위해 은행권 대출 규제를 강화하자 급전이 필요한 서민들이 카드사로 몰려들고 있다.",
      "다만 고금리 카드론 잔액이 43조원을 돌파하며 역대 최대치를 경신한 가운데, 취약차주의 이자 부담이 커지면서 연체율 상승 등 부실 폭탄으로 이어질 수 있다.",
      "◇고물가·생활고에 은행 막히자…카드론 한 달 새 2705억 급증 22일 여신금융협회에 따르면 국내 9개 카드사(롯데·비씨·삼성·신한·우리·하나·현대·국민·농협)의 카드론 잔액은 43조2534억원으로 집계됐다."
    ],
    "auto_category_candidates": [
      "대출 관련 정책/규제 변화",
      "금융사 소매 대출 전략/상품 (특히 삼성생명, 한화생명 포함)",
      "시장 방향성 (대출시장뿐만 아닌, 부동산, 증권시장 등)",
      "금리/지표 변화",
      "리스크/연체/NPL"
    ],
    "dedupe_signature": "policy regulation|market direction|rate indicator|risk npl|가계대출|가계부채|금융감독원 대출|금융소비자",
    "reason": "본문 내 대출 규제·정책 관련 키워드 확인",
    "URL": "https://www.ziksir.com/news/articleView.html?idxno=137757",
    "rating": 5
  },
  {
    "id": "top_02",
    "title": "보험사 주담대 들썩이자…한화생명 신규 접수 중단",
    "publisher": "biz.sbs.co.kr",
    "published_at": "2026-06-24T16:39:00+09:00",
    "checkyn": "Y",
    "summary": "오늘(24일) 보험업계에 따르면 한화생명은 최근 대출상담사들에게 주택담보대출 신규 접수를 중단한다고 안내했습니다. 보험사들은 통상 대출 실행 예정일 기준 약 60일 전부터 접수를 받는데, 현재 한화생명은 8월 실행분 접수를 받다가 한도를 채운 것으로 전해졌습니다. 최근 보험사 주담대에 관심이 쏠리는 배경에는 은행권 대출 규제가 있습니다.",
    "keywords": [
      "가계대출",
      "대출 규제",
      "보험사 대출",
      "은행권 대출",
      "주담대",
      "주택담보대출",
      "가계부채",
      "한국은행"
    ],
    "auto_keywords": [
      "가계대출",
      "대출 규제",
      "보험사 대출",
      "은행권 대출",
      "주담대",
      "주택담보대출",
      "가계부채",
      "한국은행"
    ],
    "auto_key_sentences": [
      "오늘(24일) 보험업계에 따르면 한화생명은 최근 대출상담사들에게 주택담보대출 신규 접수를 중단한다고 안내했습니다.",
      "보험사들은 통상 대출 실행 예정일 기준 약 60일 전부터 접수를 받는데, 현재 한화생명은 8월 실행분 접수를 받다가 한도를 채운 것으로 전해졌습니다.",
      "최근 보험사 주담대에 관심이 쏠리는 배경에는 은행권 대출 규제가 있습니다."
    ],
    "auto_category_candidates": [
      "시장 방향성 (대출시장뿐만 아닌, 부동산, 증권시장 등)",
      "대출 관련 정책/규제 변화",
      "금융사 소매 대출 전략/상품 (특히 삼성생명, 한화생명 포함)",
      "보험사 관련 이슈",
      "금리/지표 변화",
      "리스크/연체/NPL"
    ],
    "dedupe_signature": "market direction|policy regulation|insurance issue|rate indicator|risk npl|가계대출|대출 규제|보험사 대출",
    "reason": "본문 내 대출 규제·정책 관련 키워드 확인",
    "URL": "https://n.news.naver.com/mnews/article/374/0000518014?sid=101",
    "rating": 5
  },
  {
    "id": "top_03",
    "title": "3주택자 연체율 1.35% '위험'...\"매도 유도해야\"",
    "publisher": "wowtv.co.kr",
    "published_at": "2026-06-24T17:28:00+09:00",
    "checkyn": "Y",
    "summary": "다음달 기준금리 인상이 기정 사실화되고 있는 가운데, 한국은행이 대출 부실 확대에 대한 우려를 드러냈습니다. 통상 은행권에서는 대출 연체율이 1%를 넘어서면 위험신호로 간주합니다. 한국은행은 “중소기업과 부동산ㆍ도소매 업종을 중심으로 채무 상환 능력 저하가 지속될 수 있다”면서 “취약 부문의 대출 부실이 충분히 줄어들지 않은 상황에서 대출금리가 오를 경우 연체율이 높은 수준에 머무를 가능성이 있다”고 진단했습니다.",
    "keywords": [
      "대출 금리",
      "연체율",
      "은행권 대출",
      "자영업자 대출",
      "취약차주",
      "대출금리",
      "기준금리",
      "한국은행"
    ],
    "auto_keywords": [
      "대출 금리",
      "연체율",
      "은행권 대출",
      "자영업자 대출",
      "취약차주",
      "대출금리",
      "기준금리",
      "한국은행"
    ],
    "auto_key_sentences": [
      "다음달 기준금리 인상이 기정 사실화되고 있는 가운데, 한국은행이 대출 부실 확대에 대한 우려를 드러냈습니다.",
      "통상 은행권에서는 대출 연체율이 1%를 넘어서면 위험신호로 간주합니다.",
      "한국은행은 “중소기업과 부동산ㆍ도소매 업종을 중심으로 채무 상환 능력 저하가 지속될 수 있다”면서 “취약 부문의 대출 부실이 충분히 줄어들지 않은 상황에서 대출금리가 오를 경우 연체율이 높은 수준에 머무를 가능성이 있다”고 진단했습니다."
    ],
    "auto_category_candidates": [
      "금융사 소매 대출 전략/상품 (특히 삼성생명, 한화생명 포함)",
      "금리/지표 변화",
      "리스크/연체/NPL"
    ],
    "dedupe_signature": "rate indicator|risk npl|대출 금리|연체율|은행권 대출|자영업자 대출|취약차주|대출금리",
    "reason": "본문 내 연체·건전성 관련 키워드 확인",
    "URL": "https://www.wowtv.co.kr/NewsCenter/News/Read?articleId=A202606240391&t=NNv",
    "rating": 5
  },
  {
    "id": "top_04",
    "title": "빚내서 빚 갚는다...카드사, 대환대출 줄여도 열어둬도 부담",
    "publisher": "ftoday.co.kr",
    "published_at": "2026-06-24T17:36:00+09:00",
    "checkyn": "Y",
    "summary": "카드론 잔액이 역대 최대 수준으로 불어나면서, 카드빚을 갚기 위해 다시 돈을 빌리는 대환대출도 늘고 있는 것으로 나타났다. 같은 기간 카드론 대환대출 잔액은 1조6559억원으로 한 달 새 576억원 늘었다. 카드론과 대환대출, 현금서비스, 리볼빙이 동시에 늘어난 점은 카드사에 양날의 검이다.",
    "keywords": [
      "대환대출",
      "연체율",
      "카드론",
      "카드사 대출",
      "현금서비스",
      "취약차주",
      "다시 돈을 빌리는",
      "이로 인해"
    ],
    "auto_keywords": [
      "대환대출",
      "연체율",
      "카드론",
      "카드사 대출",
      "현금서비스",
      "취약차주",
      "다시 돈을 빌리는",
      "이로 인해"
    ],
    "auto_key_sentences": [
      "카드론 잔액이 역대 최대 수준으로 불어나면서, 카드빚을 갚기 위해 다시 돈을 빌리는 대환대출도 늘고 있는 것으로 나타났다.",
      "같은 기간 카드론 대환대출 잔액은 1조6559억원으로 한 달 새 576억원 늘었다.",
      "카드론과 대환대출, 현금서비스, 리볼빙이 동시에 늘어난 점은 카드사에 양날의 검이다."
    ],
    "auto_category_candidates": [
      "금융사 소매 대출 전략/상품 (특히 삼성생명, 한화생명 포함)",
      "리스크/연체/NPL",
      "금리/지표 변화"
    ],
    "dedupe_signature": "risk npl|rate indicator|대환대출|연체율|카드론|카드사 대출|현금서비스|취약차주",
    "reason": "본문 내 연체·건전성 관련 키워드 확인",
    "URL": "http://www.ftoday.co.kr/news/articleView.html?idxno=361014",
    "rating": 5
  },
  {
    "id": "top_05",
    "title": "금융당국, 삼성전자 사내대출 '촉각'…가계대출 규제 '사각지대' 논란",
    "publisher": "daily.hankooki.com",
    "published_at": "2026-06-24T14:16:00+09:00",
    "checkyn": "Y",
    "summary": "가계대출 규제가 강화되는 가운데 대기업 임직원들은 상대적으로 규제 영향을 받지 않는 사내대출을 활용할 수 있다는 점에서 형평성 논란이 불거지고 있다. 사내대출이 총부채원리금상환비율(DSR)이나 가계대출 총량 규제 적용 대상이 아니라는 점에서 사실상 규제 사각지대에 놓여 있다는 점을 지적한 것이다. 가계대출 총량 관리 기조가 이어지는 가운데 사내대출 규모가 확대될 경우 규제 형평성을 둘러싼 논란도 더욱 커질 것으로 예상된다.",
    "keywords": [
      "DSR",
      "가계대출",
      "금융위원회 대출",
      "대출 규제",
      "전세대출",
      "총부채원리금상환비율",
      "가계부채",
      "금융위원회"
    ],
    "auto_keywords": [
      "DSR",
      "가계대출",
      "금융위원회 대출",
      "대출 규제",
      "전세대출",
      "총부채원리금상환비율",
      "가계부채",
      "금융위원회"
    ],
    "auto_key_sentences": [
      "가계대출 규제가 강화되는 가운데 대기업 임직원들은 상대적으로 규제 영향을 받지 않는 사내대출을 활용할 수 있다는 점에서 형평성 논란이 불거지고 있다.",
      "사내대출이 총부채원리금상환비율(DSR)이나 가계대출 총량 규제 적용 대상이 아니라는 점에서 사실상 규제 사각지대에 놓여 있다는 점을 지적한 것이다.",
      "가계대출 총량 관리 기조가 이어지는 가운데 사내대출 규모가 확대될 경우 규제 형평성을 둘러싼 논란도 더욱 커질 것으로 예상된다."
    ],
    "auto_category_candidates": [
      "대출 관련 정책/규제 변화",
      "시장 방향성 (대출시장뿐만 아닌, 부동산, 증권시장 등)",
      "금융사 소매 대출 전략/상품 (특히 삼성생명, 한화생명 포함)",
      "금리/지표 변화",
      "리스크/연체/NPL"
    ],
    "dedupe_signature": "policy regulation|market direction|rate indicator|risk npl|dsr|가계대출|금융위원회 대출|대출 규제",
    "reason": "본문 내 대출 규제·정책 관련 키워드 확인",
    "URL": "https://daily.hankooki.com/news/articleView.html?idxno=1379374",
    "rating": 5
  },
  {
    "id": "cat5_01",
    "title": "은행권 '빚투' 전방위 조이기에도…신용대출·마통, 1조 늘었다",
    "publisher": "머니투데이",
    "published_at": "2026-06-24T17:03:00+09:00",
    "checkyn": "Y",
    "summary": "주요 은행권의 신용대출과 마이너스통장을 중심으로 '빚투' 수요가 지속해서 몰리면서 잔액이 연일 치솟는 모양새다. 24일 금융권에 따르면 5대 은행(KB국민·신한·하나·우리·NH농협)의 전일 기준 개인신용대출 잔액은 108조6771억원으로 지난 11일(108조1379억) 대비 5292억원 늘었다. 단 8영업일 만에 신용대출과 마이너스통장에서만 1조원에 육박하는 돈이 불어난 셈이다.",
    "keywords": [
      "가계부채",
      "금융위원회 대출",
      "대출 갈아타기",
      "대출 금리",
      "마이너스통장",
      "신용대출",
      "은행권 대출",
      "대출 규제"
    ],
    "auto_keywords": [
      "가계부채",
      "금융위원회 대출",
      "대출 갈아타기",
      "대출 금리",
      "마이너스통장",
      "신용대출",
      "은행권 대출",
      "대출 규제"
    ],
    "auto_key_sentences": [
      "주요 은행권의 신용대출과 마이너스통장을 중심으로 '빚투' 수요가 지속해서 몰리면서 잔액이 연일 치솟는 모양새다.",
      "24일 금융권에 따르면 5대 은행(KB국민·신한·하나·우리·NH농협)의 전일 기준 개인신용대출 잔액은 108조6771억원으로 지난 11일(108조1379억) 대비 5292억원 늘었다.",
      "단 8영업일 만에 신용대출과 마이너스통장에서만 1조원에 육박하는 돈이 불어난 셈이다."
    ],
    "auto_category_candidates": [
      "금융사 소매 대출 전략/상품 (특히 삼성생명, 한화생명 포함)",
      "대출 관련 정책/규제 변화",
      "금리/지표 변화",
      "시장 방향성 (대출시장뿐만 아닌, 부동산, 증권시장 등)",
      "리스크/연체/NPL"
    ],
    "dedupe_signature": "policy regulation|rate indicator|market direction|risk npl|가계부채|금융위원회 대출|대출 갈아타기|대출 금리",
    "reason": "본문 내 대출 규제·정책 관련 키워드 확인",
    "URL": "https://www.mt.co.kr/finance/2026/06/24/2026062416184924945",
    "rating": 5
  },
  {
    "id": "cat1_01",
    "title": "\"특이한 사금융\" 대통령이 콕 집었다...'전세대출 대수술' 어떻게?",
    "publisher": "머니투데이",
    "published_at": "2026-06-24T06:30:00+09:00",
    "checkyn": "Y",
    "summary": "금융당국이 검토 중인 전세대출 관련 규제/그래픽=김지영 이재명 대통령이 \"특이한 사금융\"이라며 \"집값 상승의 주된 원인\"으로 지목한 전세대출에 대해 금융당국이 본격적인 수술에 돌입한다. 23일 금융권에 따르면 다음 달 내놓을 부동산 종합대책에는 전세대출 규제가 담길 전망이다. 지난달 이재명 대통령이 \"전세는 특이하게 대한민국에만 있는 일종의 사금융인데 지금 사라져가는 추세는 정상화되는 과정\"이라며 \"전세대출을 많이 해준 게 집값 상승의 주된 원인\"이라고 지적한 데 대한 부연 설명인 셈이다.",
    "keywords": [
      "DSR",
      "LTV",
      "금융감독원 대출",
      "대출 규제",
      "전세대출",
      "주택시장 대출",
      "총부채원리금상환비율",
      "금융감독원"
    ],
    "auto_keywords": [
      "DSR",
      "LTV",
      "금융감독원 대출",
      "대출 규제",
      "전세대출",
      "주택시장 대출",
      "총부채원리금상환비율",
      "금융감독원"
    ],
    "auto_key_sentences": [
      "금융당국이 검토 중인 전세대출 관련 규제/그래픽=김지영 이재명 대통령이 \"특이한 사금융\"이라며 \"집값 상승의 주된 원인\"으로 지목한 전세대출에 대해 금융당국이 본격적인 수술에 돌입한다.",
      "23일 금융권에 따르면 다음 달 내놓을 부동산 종합대책에는 전세대출 규제가 담길 전망이다.",
      "지난달 이재명 대통령이 \"전세는 특이하게 대한민국에만 있는 일종의 사금융인데 지금 사라져가는 추세는 정상화되는 과정\"이라며 \"전세대출을 많이 해준 게 집값 상승의 주된 원인\"이라고 지적한 데 대한 부연 설명인 셈이다."
    ],
    "auto_category_candidates": [
      "대출 관련 정책/규제 변화",
      "시장 방향성 (대출시장뿐만 아닌, 부동산, 증권시장 등)"
    ],
    "dedupe_signature": "policy regulation|market direction|dsr|ltv|금융감독원 대출|대출 규제|전세대출|주택시장 대출",
    "reason": "본문 내 대출 규제·정책 관련 키워드 확인",
    "URL": "https://www.mt.co.kr/finance/2026/06/24/2026062316565945986",
    "rating": 5
  },
  {
    "id": "cat1_02",
    "title": "\"3주택 이상 차주, 연체율 악화 뚜렷\"⋯'빚으로 쌓은 자산' 우려 [한은 ...",
    "publisher": "etoday.co.kr",
    "published_at": "2026-06-24T16:50:00+09:00",
    "checkyn": "Y",
    "summary": "한은은 대출을 받아 집을 여러 채 구입한 다주택자에 대해서도 자산건전성 악화에 대한 강한 우려를 표했다. 3주택 이상을 보유한 다주택 차주들의 연체율 악화도 두드러졌다. 한은 분석 결과 올해 1분기 말 기준 3주택 이상 차주의 평균 연체율은 1.35%로 1주택자(0.52%)의 두 배를 웃돌았다.",
    "keywords": [
      "DSR",
      "가계대출",
      "금융위원회 대출",
      "연체율",
      "대출금리",
      "기준금리",
      "시장금리",
      "가계부채"
    ],
    "auto_keywords": [
      "DSR",
      "가계대출",
      "금융위원회 대출",
      "연체율",
      "대출금리",
      "기준금리",
      "시장금리",
      "가계부채"
    ],
    "auto_key_sentences": [
      "한은은 대출을 받아 집을 여러 채 구입한 다주택자에 대해서도 자산건전성 악화에 대한 강한 우려를 표했다.",
      "3주택 이상을 보유한 다주택 차주들의 연체율 악화도 두드러졌다.",
      "한은 분석 결과 올해 1분기 말 기준 3주택 이상 차주의 평균 연체율은 1.35%로 1주택자(0.52%)의 두 배를 웃돌았다."
    ],
    "auto_category_candidates": [
      "대출 관련 정책/규제 변화",
      "금리/지표 변화",
      "시장 방향성 (대출시장뿐만 아닌, 부동산, 증권시장 등)",
      "리스크/연체/NPL"
    ],
    "dedupe_signature": "policy regulation|rate indicator|market direction|risk npl|dsr|가계대출|금융위원회 대출|연체율",
    "reason": "본문 내 연체·건전성 관련 키워드 확인",
    "URL": "https://www.etoday.co.kr/news/view/2596811",
    "rating": 5
  },
  {
    "id": "cat5_02",
    "title": "카드론 역대 최대 속 연체회수비 1900억대 고착",
    "publisher": "kbanker.co.kr",
    "published_at": "2026-06-24T16:54:00+09:00",
    "checkyn": "Y",
    "summary": "여기에 카드론 잔액마저 역대 최대치로 늘어나면서 카드사들의 연체채권 관리 부담도 쉽게 낮아지기 어려울 전망이다. 여신금융협회에 따르면 카드사 9곳의 지난달 말 카드론 잔액은 43조2534억원으로 역대 최대치를 기록했다. 은행권 대출 규제에 따른 풍선효과와 투자자금 수요 등이 맞물리며 카드론 잔액이 다시 늘어난 것으로 풀이된다.",
    "keywords": [
      "대출 규제",
      "대환대출",
      "연체율",
      "은행권 대출",
      "채무조정",
      "카드론",
      "카드사 대출",
      "현금서비스"
    ],
    "auto_keywords": [
      "대출 규제",
      "대환대출",
      "연체율",
      "은행권 대출",
      "채무조정",
      "카드론",
      "카드사 대출",
      "현금서비스"
    ],
    "auto_key_sentences": [
      "여기에 카드론 잔액마저 역대 최대치로 늘어나면서 카드사들의 연체채권 관리 부담도 쉽게 낮아지기 어려울 전망이다.",
      "여신금융협회에 따르면 카드사 9곳의 지난달 말 카드론 잔액은 43조2534억원으로 역대 최대치를 기록했다.",
      "은행권 대출 규제에 따른 풍선효과와 투자자금 수요 등이 맞물리며 카드론 잔액이 다시 늘어난 것으로 풀이된다."
    ],
    "auto_category_candidates": [
      "금융사 소매 대출 전략/상품 (특히 삼성생명, 한화생명 포함)",
      "대출 관련 정책/규제 변화",
      "리스크/연체/NPL",
      "금리/지표 변화"
    ],
    "dedupe_signature": "policy regulation|risk npl|rate indicator|대출 규제|대환대출|연체율|은행권 대출|채무조정",
    "reason": "본문 내 대출 규제·정책 관련 키워드 확인",
    "URL": "https://www.kbanker.co.kr/news/articleView.html?idxno=225282",
    "rating": 5
  },
  {
    "id": "cat3_01",
    "title": "강원 가계대출 증가세 여전… 은행권 '주담대 조이기' 확산되나",
    "publisher": "kado.net",
    "published_at": "2026-06-25T00:10:00+09:00",
    "checkyn": "Y",
    "summary": "은행권의 높은 대출 문턱에도 강원도내 가계대출 증가세가 주택담보대출을 중심으로 꺾이지 않는 것으로 나타났다. 이에 추후 가계대출 총량 관리를 위한 ‘주담대 조이기’가 확대될 것이라는 전망이 나온다. 24일 한국은행 강원본부가 발표한 금융기관 여수신 동향을 보면 4월 중 강원지역 내 가계대출은 930억원 증가한 것으로 나타났다.",
    "keywords": [
      "가계대출",
      "대출 갈아타기",
      "은행권 대출",
      "주담대",
      "주택담보대출",
      "한국은행",
      "주담대 조이기",
      "총량 관리를 위한"
    ],
    "auto_keywords": [
      "가계대출",
      "대출 갈아타기",
      "은행권 대출",
      "주담대",
      "주택담보대출",
      "한국은행",
      "주담대 조이기",
      "총량 관리를 위한"
    ],
    "auto_key_sentences": [
      "은행권의 높은 대출 문턱에도 강원도내 가계대출 증가세가 주택담보대출을 중심으로 꺾이지 않는 것으로 나타났다.",
      "이에 추후 가계대출 총량 관리를 위한 ‘주담대 조이기’가 확대될 것이라는 전망이 나온다.",
      "24일 한국은행 강원본부가 발표한 금융기관 여수신 동향을 보면 4월 중 강원지역 내 가계대출은 930억원 증가한 것으로 나타났다."
    ],
    "auto_category_candidates": [
      "시장 방향성 (대출시장뿐만 아닌, 부동산, 증권시장 등)",
      "금융사 소매 대출 전략/상품 (특히 삼성생명, 한화생명 포함)"
    ],
    "dedupe_signature": "market direction|가계대출|대출 갈아타기|은행권 대출|주담대|주택담보대출|한국은행|주담대 조이기",
    "reason": "본문 내 금리·지표 관련 키워드 확인",
    "URL": "https://www.kado.net/news/articleView.html?idxno=2057740",
    "rating": 5
  },
  {
    "id": "cat3_02",
    "title": "[금융안정보고서] 자영업 대출 1095.5조…취약차주 연체율 12.68%",
    "publisher": "metroseoul.co.kr",
    "published_at": "2026-06-24T11:26:00+09:00",
    "checkyn": "Y",
    "summary": "부동산업 개인사업자대출 163.5조…취약 대출 집중 60대 이상 금융부채 405.7조…비은행 부실 전이 우려 국내 자영업자 대출이 1100조원에 육박한 가운데 취약 자영업자의 연체율이 12%를 넘어선 것으로 나타났다. 전체 자영업자 대출 연체율은 1분기 말 2.04%였지만 저소득 또는 저신용 다중채무자인 취약 자영업자의 연체율은 12.68%까지 상승했다. 취약 자영업자 연체율은 2022년 2분기 말 4.93%에서 올해 1분기 말 12.68%로 7.75%포인트 상승했다.",
    "keywords": [
      "부동산 대출",
      "연체율",
      "저축은행 대출",
      "취약차주",
      "가계대출",
      "자영업자 대출",
      "시장금리",
      "가계부채"
    ],
    "auto_keywords": [
      "부동산 대출",
      "연체율",
      "저축은행 대출",
      "취약차주",
      "가계대출",
      "자영업자 대출",
      "시장금리",
      "가계부채"
    ],
    "auto_key_sentences": [
      "부동산업 개인사업자대출 163.5조…취약 대출 집중 60대 이상 금융부채 405.7조…비은행 부실 전이 우려 국내 자영업자 대출이 1100조원에 육박한 가운데 취약 자영업자의 연체율이 12%를 넘어선 것으로 나타났다.",
      "전체 자영업자 대출 연체율은 1분기 말 2.04%였지만 저소득 또는 저신용 다중채무자인 취약 자영업자의 연체율은 12.68%까지 상승했다.",
      "취약 자영업자 연체율은 2022년 2분기 말 4.93%에서 올해 1분기 말 12.68%로 7.75%포인트 상승했다."
    ],
    "auto_category_candidates": [
      "시장 방향성 (대출시장뿐만 아닌, 부동산, 증권시장 등)",
      "리스크/연체/NPL",
      "금융사 소매 대출 전략/상품 (특히 삼성생명, 한화생명 포함)",
      "금리/지표 변화"
    ],
    "dedupe_signature": "market direction|risk npl|rate indicator|부동산 대출|연체율|저축은행 대출|취약차주|가계대출",
    "reason": "본문 내 대출 규제·정책 관련 키워드 확인",
    "URL": "http://www.metroseoul.co.kr/article/20260624500173",
    "rating": 5
  },
  {
    "id": "cat5_03",
    "title": "[이슈] '만점 신용'도 못 피했다…마이너스통장 금리 5% 눈앞",
    "publisher": "startuptoday.co.kr",
    "published_at": "2026-06-24T10:24:00+09:00",
    "checkyn": "Y",
    "summary": "고신용자에게 적용되는 마이너스통장 금리가 연 5% 수준까지 오르면서 우량 차주의 이자 부담도 커지고 있다. 시장금리 상승세가 이어지는 가운데 은행권이 신용대출 관리 강도를 높이면서 고신용자 우대 효과도 예전만 못하다는 평가가 나온다.24일 은행연합회에 따르면 KB국민·신한·하나·우리·NH농협은행의 지난 4월 신용한도대출(마이너스통장) 금리는 신용점수 901~950점 차주 기준 연 4.57~5.27%로 집계됐다. 5개 은행 평균은 연 4.96%다.은행별로는 우리은행이 연 5.27%로 가장 높았고 NH농협은행(5.07%), 신한은행(5",
    "keywords": [
      "고신용자",
      "마이너스통장",
      "신용대출",
      "신용점수",
      "시장금리",
      "한은",
      "차주의 이자 부담도",
      "고신용자 우대 효과도"
    ],
    "auto_keywords": [
      "고신용자",
      "마이너스통장",
      "신용대출",
      "신용점수",
      "시장금리",
      "한은",
      "차주의 이자 부담도",
      "고신용자 우대 효과도"
    ],
    "auto_key_sentences": [
      "고신용자에게 적용되는 마이너스통장 금리가 연 5% 수준까지 오르면서 우량 차주의 이자 부담도 커지고 있다.",
      "시장금리 상승세가 이어지는 가운데 은행권이 신용대출 관리 강도를 높이면서 고신용자 우대 효과도 예전만 못하다는 평가가 나온다.24일 은행연합회에 따르면 KB국민·신한·하나·우리·NH농협은행의 지난 4월 신용한도대출(마이너스통장) 금리는 신용점수 901~950점 차주 기준 연 4.57~5.27%로 집계됐다.",
      "5개 은행 평균은 연 4.96%다.은행별로는 우리은행이 연 5.27%로 가장 높았고 NH농협은행(5.07%), 신한은행(5"
    ],
    "auto_category_candidates": [
      "금융사 소매 대출 전략/상품 (특히 삼성생명, 한화생명 포함)",
      "시장 방향성 (대출시장뿐만 아닌, 부동산, 증권시장 등)"
    ],
    "dedupe_signature": "market direction|고신용자|마이너스통장|신용대출|신용점수|시장금리|한은|차주의 이자 부담도",
    "reason": "본문 내 금리·지표 관련 키워드 확인",
    "URL": "https://www.startuptoday.co.kr/news/articleView.html?idxno=804462",
    "rating": 5
  },
  {
    "id": "cat3_03",
    "title": "대출 문턱 높아져도 '빚투'는 지속…6월 5대 은행 가계대출 4.1조 급증",
    "publisher": "pressian.com",
    "published_at": "2026-06-24T05:29:00+09:00",
    "checkyn": "Y",
    "summary": "대출 문턱 높아져도 '빚투'는 지속…6월 5대 은행 가계대출 4.1조 급증 은행권의 대출 규제가 강화되고 대출금리가 오르고 있음에도 시중은행 가계대출 증가세가 멈추지 않고 있다. 23일 금융권에 따르면 5대 시중은행(KB국민·신한·하나·우리·NH농협)의 이달 신용대출 잔액(22일 기준)은 108조3116억 원으로 집계됐다. 이에 따라 신용대출과 주담대를 합산한 5대 은행의 총 가계대출 잔액은 22일 기준 전월(770조8229억 원)보다 4조1031억 원 늘어난 774조9260억 원으로 집계됐다.",
    "keywords": [
      "가계대출",
      "대출 규제",
      "대출 금리",
      "마이너스통장",
      "신용대출",
      "은행권 대출",
      "주담대",
      "주택담보대출"
    ],
    "auto_keywords": [
      "가계대출",
      "대출 규제",
      "대출 금리",
      "마이너스통장",
      "신용대출",
      "은행권 대출",
      "주담대",
      "주택담보대출"
    ],
    "auto_key_sentences": [
      "대출 문턱 높아져도 '빚투'는 지속…6월 5대 은행 가계대출 4.1조 급증 은행권의 대출 규제가 강화되고 대출금리가 오르고 있음에도 시중은행 가계대출 증가세가 멈추지 않고 있다.",
      "23일 금융권에 따르면 5대 시중은행(KB국민·신한·하나·우리·NH농협)의 이달 신용대출 잔액(22일 기준)은 108조3116억 원으로 집계됐다.",
      "이에 따라 신용대출과 주담대를 합산한 5대 은행의 총 가계대출 잔액은 22일 기준 전월(770조8229억 원)보다 4조1031억 원 늘어난 774조9260억 원으로 집계됐다."
    ],
    "auto_category_candidates": [
      "시장 방향성 (대출시장뿐만 아닌, 부동산, 증권시장 등)",
      "금융사 소매 대출 전략/상품 (특히 삼성생명, 한화생명 포함)",
      "대출 관련 정책/규제 변화",
      "금리/지표 변화"
    ],
    "dedupe_signature": "market direction|policy regulation|rate indicator|가계대출|대출 규제|대출 금리|마이너스통장|신용대출",
    "reason": "본문 내 대출 규제·정책 관련 키워드 확인",
    "URL": "https://www.pressian.com/pages/articles/2026062404532222363",
    "rating": 5
  },
  {
    "id": "cat5_04",
    "title": "우량차주 이탈 우려에 수신 경쟁까지···저축은행 '이중고'",
    "publisher": "enewstoday.co.kr",
    "published_at": "2026-06-24T15:00:00+09:00",
    "checkyn": "Y",
    "summary": "[이뉴스투데이 전주영 기자] 은행권의 중금리대출 확대와 증시 활황에 따른 자금 이동이 동시에 나타나면서 저축은행업권의 고민이 깊어지고 있다. 애큐온저축은행과 페퍼저축은행 등 자산 규모가 큰 저축은행들도 4%대 예금 상품을 선보이며 수신 경쟁에 뛰어들었다. 한국은행 경제통계시스템에 따르면 지난 4월 말 기준 저축은행 수신 잔액은 100조6607억원으로 집계됐다.",
    "keywords": [
      "대출 규제",
      "대환대출",
      "연체율",
      "은행권 대출",
      "저신용자",
      "저축은행 대출",
      "중금리대출",
      "한국은행"
    ],
    "auto_keywords": [
      "대출 규제",
      "대환대출",
      "연체율",
      "은행권 대출",
      "저신용자",
      "저축은행 대출",
      "중금리대출",
      "한국은행"
    ],
    "auto_key_sentences": [
      "[이뉴스투데이 전주영 기자] 은행권의 중금리대출 확대와 증시 활황에 따른 자금 이동이 동시에 나타나면서 저축은행업권의 고민이 깊어지고 있다.",
      "애큐온저축은행과 페퍼저축은행 등 자산 규모가 큰 저축은행들도 4%대 예금 상품을 선보이며 수신 경쟁에 뛰어들었다.",
      "한국은행 경제통계시스템에 따르면 지난 4월 말 기준 저축은행 수신 잔액은 100조6607억원으로 집계됐다."
    ],
    "auto_category_candidates": [
      "금융사 소매 대출 전략/상품 (특히 삼성생명, 한화생명 포함)",
      "대출 관련 정책/규제 변화",
      "리스크/연체/NPL",
      "금리/지표 변화"
    ],
    "dedupe_signature": "policy regulation|risk npl|rate indicator|대출 규제|대환대출|연체율|은행권 대출|저신용자",
    "reason": "본문 내 금리·지표 관련 키워드 확인",
    "URL": "http://www.enewstoday.co.kr/news/articleView.html?idxno=2441996",
    "rating": 5
  },
  {
    "id": "cat5_05",
    "title": "중·저신용자 숨통 트일까…저축은행 '생활안정자금' 시동",
    "publisher": "dailian.co.kr",
    "published_at": "2026-06-24T07:05:00+09:00",
    "checkyn": "Y",
    "summary": "저축은행업계가 중·저신용자의 자금 접근성을 높이기 위한 생활안정자금 대출 상품 출시를 앞두고 있다. 24일 금융권에 따르면 저축은행업계는 이달 말부터 중·저신용자 대상 생활안정자금 대출 상품을 순차적으로 선보인다. 한 저축은행업계 관계자는 \"기존에는 연소득 이내 규제로 막혔던 차주들이 있었지만, 생활안정자금 대출은 해당 한도 제한을 받지 않는다는 점에서 의미가 있다\"며 \"중저신용자의 대출 공급에 숨통이 트일 수 있다\"고 말했다.",
    "keywords": [
      "가계부채",
      "대출 규제",
      "신용대출",
      "신용점수",
      "연체율",
      "저신용자",
      "저축은행 대출",
      "중금리대출"
    ],
    "auto_keywords": [
      "가계부채",
      "대출 규제",
      "신용대출",
      "신용점수",
      "연체율",
      "저신용자",
      "저축은행 대출",
      "중금리대출"
    ],
    "auto_key_sentences": [
      "저축은행업계가 중·저신용자의 자금 접근성을 높이기 위한 생활안정자금 대출 상품 출시를 앞두고 있다.",
      "24일 금융권에 따르면 저축은행업계는 이달 말부터 중·저신용자 대상 생활안정자금 대출 상품을 순차적으로 선보인다.",
      "한 저축은행업계 관계자는 \"기존에는 연소득 이내 규제로 막혔던 차주들이 있었지만, 생활안정자금 대출은 해당 한도 제한을 받지 않는다는 점에서 의미가 있다\"며 \"중저신용자의 대출 공급에 숨통이 트일 수 있다\"고 말했다."
    ],
    "auto_category_candidates": [
      "금융사 소매 대출 전략/상품 (특히 삼성생명, 한화생명 포함)",
      "리스크/연체/NPL",
      "대출 관련 정책/규제 변화",
      "금리/지표 변화",
      "시장 방향성 (대출시장뿐만 아닌, 부동산, 증권시장 등)"
    ],
    "dedupe_signature": "risk npl|policy regulation|rate indicator|market direction|가계부채|대출 규제|신용대출|신용점수",
    "reason": "본문 내 대출 규제·정책 관련 키워드 확인",
    "URL": "https://www.dailian.co.kr/news/view/1658881?sc=Naver",
    "rating": 5
  },
  {
    "id": "cat2_01",
    "title": "[사설] 청년은 신용대출, 고령층은 사업부채 허덕… ‘빚의 역습’ 대비...",
    "publisher": "hankookilbo.com",
    "published_at": "2026-06-25T00:10:00+09:00",
    "checkyn": "Y",
    "summary": "[사설] 청년은 신용대출, 고령층은 사업부채 허덕… ‘빚의 역습’ 대비를 청년, 고령층, 자영업자 등 취약계층을 중심으로 부채 경고음이 커지고 있다. 청년 연체율이 높고, 고령층 자영업자 부채는 10년 만에 네 배 이상 급증해 400조 원을 돌파했다. 은퇴 후 자영업에 내몰린 고령층이 사업부채에 허덕인다면, 청년들은 신용대출을 갚지 못해 어려움을 겪는다.",
    "keywords": [
      "가계대출",
      "대출 금리",
      "신용대출",
      "연체율",
      "자영업자 대출",
      "채무조정",
      "한국은행",
      "고령층은 사업부채 허덕"
    ],
    "auto_keywords": [
      "가계대출",
      "대출 금리",
      "신용대출",
      "연체율",
      "자영업자 대출",
      "채무조정",
      "한국은행",
      "고령층은 사업부채 허덕"
    ],
    "auto_key_sentences": [
      "[사설] 청년은 신용대출, 고령층은 사업부채 허덕… ‘빚의 역습’ 대비를 청년, 고령층, 자영업자 등 취약계층을 중심으로 부채 경고음이 커지고 있다.",
      "청년 연체율이 높고, 고령층 자영업자 부채는 10년 만에 네 배 이상 급증해 400조 원을 돌파했다.",
      "은퇴 후 자영업에 내몰린 고령층이 사업부채에 허덕인다면, 청년들은 신용대출을 갚지 못해 어려움을 겪는다."
    ],
    "auto_category_candidates": [
      "금리/지표 변화",
      "시장 방향성 (대출시장뿐만 아닌, 부동산, 증권시장 등)",
      "리스크/연체/NPL",
      "금융사 소매 대출 전략/상품 (특히 삼성생명, 한화생명 포함)"
    ],
    "dedupe_signature": "rate indicator|market direction|risk npl|가계대출|대출 금리|신용대출|연체율|자영업자 대출",
    "reason": "본문 내 연체·건전성 관련 키워드 확인",
    "URL": "https://www.hankookilbo.com/news/article/A2026062414560005731?did=NA",
    "rating": 5
  },
  {
    "id": "cat6_01",
    "title": "빚투에 보험계약대출도 급증 … 금융당국 \"보험사 긴급 소집\"",
    "publisher": "매일경제",
    "published_at": "2026-06-24T18:05:00+09:00",
    "checkyn": "Y",
    "summary": "가계대출 증가세와 관련해 금융당국의 비상관리 회의 대상이 되어 보험계약대출 현황을 점검받고 있습니다. 금융당국은 최근 급증하는 보험계약대출과 카드론 증가세를 주시하며 가계부채 관리에 대한 비상 체제에 돌입했어요. 🚨 2026년 6월 25일에는 보험사들을 긴급 소집해 가계부채 비상 관리 회의를 열 예정이며, 향후 여신전문금융회사도 호출할 계획이라고 해요.",
    "keywords": [
      "가계대출",
      "가계부채",
      "보험계약대출",
      "보험사 대출",
      "생명보험 대출",
      "카드론",
      "카드사 대출",
      "생명보험"
    ],
    "auto_keywords": [
      "가계대출",
      "가계부채",
      "보험계약대출",
      "보험사 대출",
      "생명보험 대출",
      "카드론",
      "카드사 대출",
      "생명보험"
    ],
    "auto_key_sentences": [
      "가계대출 증가세와 관련해 금융당국의 비상관리 회의 대상이 되어 보험계약대출 현황을 점검받고 있습니다.",
      "금융당국은 최근 급증하는 보험계약대출과 카드론 증가세를 주시하며 가계부채 관리에 대한 비상 체제에 돌입했어요.",
      "🚨 2026년 6월 25일에는 보험사들을 긴급 소집해 가계부채 비상 관리 회의를 열 예정이며, 향후 여신전문금융회사도 호출할 계획이라고 해요."
    ],
    "auto_category_candidates": [
      "보험사 관련 이슈",
      "금융사 소매 대출 전략/상품 (특히 삼성생명, 한화생명 포함)",
      "시장 방향성 (대출시장뿐만 아닌, 부동산, 증권시장 등)",
      "금리/지표 변화",
      "리스크/연체/NPL"
    ],
    "dedupe_signature": "insurance issue|market direction|rate indicator|risk npl|가계대출|가계부채|보험계약대출|보험사 대출",
    "reason": "제목·본문·키워드 기준 소매여신 관련성 확인",
    "URL": "https://www.mk.co.kr/article/12082218",
    "rating": 5
  },
  {
    "id": "cat3_04",
    "title": "은행서 막힌 주담대 보험사 이동…'대체창구' 부상",
    "publisher": "businessplus.kr",
    "published_at": "2026-06-24T14:54:00+09:00",
    "checkyn": "Y",
    "summary": "은행권의 주택담보대출 관리 강화와 금리 상승으로 대출 수요가 제2금융권으로 이동하는 흐름에 맞춰 보험사가 새로운 주택금융 공급 채널로 부상하고 있다. 금융감독원 금융상품통합비교공시 자료 기준 보험사 주담대 평균 금리는 지난해 11월 4.67%, 12월 4.76%, 올 1월 4.83%, 2월 4.95%로 상승했다. 24일 기준 각 보험사 주택담보대출 금리 공시 기준 삼성생명의 주담대 금리는 연 5.3~6.8% 수준이다.",
    "keywords": [
      "가계대출",
      "교보생명",
      "금융감독원 대출",
      "금융위원회 대출",
      "대출 금리",
      "보험계약대출",
      "보험사 대출",
      "생명보험 대출"
    ],
    "auto_keywords": [
      "가계대출",
      "교보생명",
      "금융감독원 대출",
      "금융위원회 대출",
      "대출 금리",
      "보험계약대출",
      "보험사 대출",
      "생명보험 대출"
    ],
    "auto_key_sentences": [
      "은행권의 주택담보대출 관리 강화와 금리 상승으로 대출 수요가 제2금융권으로 이동하는 흐름에 맞춰 보험사가 새로운 주택금융 공급 채널로 부상하고 있다.",
      "금융감독원 금융상품통합비교공시 자료 기준 보험사 주담대 평균 금리는 지난해 11월 4.67%, 12월 4.76%, 올 1월 4.83%, 2월 4.95%로 상승했다.",
      "24일 기준 각 보험사 주택담보대출 금리 공시 기준 삼성생명의 주담대 금리는 연 5.3~6.8% 수준이다."
    ],
    "auto_category_candidates": [
      "시장 방향성 (대출시장뿐만 아닌, 부동산, 증권시장 등)",
      "보험사 관련 이슈",
      "대출 관련 정책/규제 변화",
      "금리/지표 변화",
      "금융사 소매 대출 전략/상품 (특히 삼성생명, 한화생명 포함)"
    ],
    "dedupe_signature": "market direction|insurance issue|policy regulation|rate indicator|가계대출|교보생명|금융감독원 대출|금융위원회 대출",
    "reason": "본문 내 대출 규제·정책 관련 키워드 확인",
    "URL": "https://www.businessplus.kr/news/articleView.html?idxno=113260",
    "rating": 5
  },
  {
    "id": "cat5_06",
    "title": "한은 \"금융시스템 안정적\"…집값·빚투·취약차주 리스크는 경고",
    "publisher": "ziksir.com",
    "published_at": "2026-06-24T15:10:00+09:00",
    "checkyn": "Y",
    "summary": "[직썰 / 손성은 기자] 한국은행이 국내 금융시스템에 대해 ‘대체로 안정적’이라고 평가했다. 다만 서울 등 수도권 주택가격 상승세 재확대와 차입을 통한 자산투자 증가, 취약차주 부실 위험 확대 가능성은 주요 불안 요인으로 지목했다. 한은은 24일 발표한 ‘2026년 6월 금융안정보고서’에서 중동 지역 지정학적 리스크와 국제금융시장 불확실성에도 국내 금융시스템이 전반적으로 안정적인 상태를 유지하고 있다고 진단했다.",
    "keywords": [
      "가계대출",
      "보험사 대출",
      "연체율",
      "자영업자 대출",
      "저축은행 대출",
      "주택시장 대출",
      "취약차주",
      "시장금리"
    ],
    "auto_keywords": [
      "가계대출",
      "보험사 대출",
      "연체율",
      "자영업자 대출",
      "저축은행 대출",
      "주택시장 대출",
      "취약차주",
      "시장금리"
    ],
    "auto_key_sentences": [
      "[직썰 / 손성은 기자] 한국은행이 국내 금융시스템에 대해 ‘대체로 안정적’이라고 평가했다.",
      "다만 서울 등 수도권 주택가격 상승세 재확대와 차입을 통한 자산투자 증가, 취약차주 부실 위험 확대 가능성은 주요 불안 요인으로 지목했다.",
      "한은은 24일 발표한 ‘2026년 6월 금융안정보고서’에서 중동 지역 지정학적 리스크와 국제금융시장 불확실성에도 국내 금융시스템이 전반적으로 안정적인 상태를 유지하고 있다고 진단했다."
    ],
    "auto_category_candidates": [
      "금융사 소매 대출 전략/상품 (특히 삼성생명, 한화생명 포함)",
      "시장 방향성 (대출시장뿐만 아닌, 부동산, 증권시장 등)",
      "리스크/연체/NPL",
      "보험사 관련 이슈",
      "금리/지표 변화"
    ],
    "dedupe_signature": "market direction|risk npl|insurance issue|rate indicator|가계대출|보험사 대출|연체율|자영업자 대출",
    "reason": "본문 내 연체·건전성 관련 키워드 확인",
    "URL": "https://www.ziksir.com/news/articleView.html?idxno=137880",
    "rating": 5
  },
  {
    "id": "cat3_05",
    "title": "은행 대신 보험사 찾았는데…금리 오르고 접수 중단",
    "publisher": "biz.sbs.co.kr",
    "published_at": "2026-06-24T15:45:00+09:00",
    "checkyn": "Y",
    "summary": "[앵커] 주요 보험사들이 주택담보대출 금리를 올리고 신규 접수를 중단하는 등 가계대출 문턱을 높이고 있습니다. 은행권이 주담대 금리를 올리고 한도를 줄이는 등 총량관리에 나서자 보험사로 수요가 쏠리는 풍선효과를 차단하기 위한 것으로 보이는데요. 이에 따라 주담대 금리 하단은 5%대 중반으로 올랐고, 일부 지점은 주담대 신규 접수도 중단했습니다.",
    "keywords": [
      "DSR",
      "가계대출",
      "대출 금리",
      "보험사 대출",
      "은행권 대출",
      "주담대",
      "주택담보대출",
      "한화생명"
    ],
    "auto_keywords": [
      "DSR",
      "가계대출",
      "대출 금리",
      "보험사 대출",
      "은행권 대출",
      "주담대",
      "주택담보대출",
      "한화생명"
    ],
    "auto_key_sentences": [
      "[앵커] 주요 보험사들이 주택담보대출 금리를 올리고 신규 접수를 중단하는 등 가계대출 문턱을 높이고 있습니다.",
      "은행권이 주담대 금리를 올리고 한도를 줄이는 등 총량관리에 나서자 보험사로 수요가 쏠리는 풍선효과를 차단하기 위한 것으로 보이는데요.",
      "이에 따라 주담대 금리 하단은 5%대 중반으로 올랐고, 일부 지점은 주담대 신규 접수도 중단했습니다."
    ],
    "auto_category_candidates": [
      "시장 방향성 (대출시장뿐만 아닌, 부동산, 증권시장 등)",
      "금리/지표 변화",
      "금융사 소매 대출 전략/상품 (특히 삼성생명, 한화생명 포함)",
      "보험사 관련 이슈",
      "대출 관련 정책/규제 변화"
    ],
    "dedupe_signature": "market direction|rate indicator|insurance issue|policy regulation|dsr|가계대출|대출 금리|보험사 대출",
    "reason": "본문 내 대출 규제·정책 관련 키워드 확인",
    "URL": "https://n.news.naver.com/mnews/article/374/0000518002?sid=101",
    "rating": 4
  }
]